openapi_client/__init__.py
openapi_client/api_client.py
openapi_client/api_response.py
openapi_client/configuration.py
openapi_client/exceptions.py
openapi_client/py.typed
openapi_client/rest.py
openapi_client/api/__init__.py
openapi_client/api/completion_generation_api.py
openapi_client/api/metadata_api.py
openapi_client/api/public_prompts_api.py
openapi_client/api/public_tags_api.py
openapi_client/models/__init__.py
openapi_client/models/author.py
openapi_client/models/binding_type.py
openapi_client/models/chat_completion_request.py
openapi_client/models/chat_completion_response.py
openapi_client/models/direct_completion_request.py
openapi_client/models/direct_completion_response.py
openapi_client/models/document.py
openapi_client/models/document_content.py
openapi_client/models/document_metadata.py
openapi_client/models/error.py
openapi_client/models/error_message.py
openapi_client/models/http_validation_error.py
openapi_client/models/location_inner.py
openapi_client/models/message.py
openapi_client/models/metadata_info.py
openapi_client/models/model_params.py
openapi_client/models/model_settings.py
openapi_client/models/position.py
openapi_client/models/prompt_config.py
openapi_client/models/prompt_template_variable.py
openapi_client/models/prompt_template_with_variables.py
openapi_client/models/rag_config.py
openapi_client/models/tag.py
openapi_client/models/tag_category_with_tags.py
openapi_client/models/tags_type.py
openapi_client/models/validation_error.py
genaisdk-1.0.1.dist-info/METADATA
genaisdk-1.0.1.dist-info/WHEEL
genaisdk-1.0.1.dist-info/top_level.txt
genaisdk-1.0.1.dist-info/RECORD
